pyslime/__init__.py
pyslime/fields.py
pyslime/slime.py
pyslime/slimeVis.py
pyslime/utils.py
pyslime/scripts/__init__.py
pyslime/scripts/plot_distribution.py
pyslime-0.1.data/scripts/pyslime_plot_distribution
pyslime-0.1.dist-info/LICENSE
pyslime-0.1.dist-info/METADATA
pyslime-0.1.dist-info/WHEEL
pyslime-0.1.dist-info/top_level.txt
pyslime-0.1.dist-info/RECORD
